checkatlas/__init__.py
checkatlas/__main__.py
checkatlas/atlas.py
checkatlas/cellranger.py
checkatlas/check.py
checkatlas/checkatlas_workflow.py
checkatlas/metrics/__init__.py
checkatlas/metrics/annot/__init__.py
checkatlas/metrics/annot/adj_mutual_info.py
checkatlas/metrics/annot/adj_rand_index.py
checkatlas/metrics/annot/dunn_index.py
checkatlas/metrics/annot/fowlkes_mallows.py
checkatlas/metrics/annot/isolated_f1_score.py
checkatlas/metrics/annot/mutual_info.py
checkatlas/metrics/annot/normalized_mutual_info.py
checkatlas/metrics/annot/rand_index.py
checkatlas/metrics/annot/vmeasure.py
checkatlas/metrics/cluster/__init__.py
checkatlas/metrics/cluster/calinski_harabasz.py
checkatlas/metrics/cluster/davies_bouldin.py
checkatlas/metrics/cluster/silhouette.py
checkatlas/metrics/denoising/__init__.py
checkatlas/metrics/denoising/mse.py
checkatlas/metrics/denoising/poisson.py
checkatlas/metrics/dimred/__init__.py
checkatlas/metrics/dimred/entourage.py
checkatlas/metrics/dimred/kruskal_stress.py
checkatlas/metrics/dimred/spearman_rho.py
checkatlas/metrics/metrics.py
checkatlas/metrics/specificity/__init__.py
checkatlas/metrics/specificity/analysis.py
checkatlas/metrics/specificity/compute.py
checkatlas/metrics/specificity/get_data.py
checkatlas/metrics/specificity/plot.py
checkatlas/seurat.py
checkatlas/utils/VERSION
checkatlas/utils/__init__.py
checkatlas/utils/checkatlas_arguments.py
checkatlas/utils/checkatlas_workflow_arguments.py
checkatlas/utils/files.py
checkatlas/utils/folders.py
checkatlas/utils/obsolete_arguments.py
pyproject.toml
checkatlas-0.7.1.dist-info/LICENSE
checkatlas-0.7.1.dist-info/METADATA
checkatlas-0.7.1.dist-info/WHEEL
checkatlas-0.7.1.dist-info/entry_points.txt
checkatlas-0.7.1.dist-info/RECORD
