Metadata-Version: 2.1
Name: checkatlas
Version: 0.7.1
Summary: One liner tool to check the quality of your single-cell atlases.
Home-page: https://checkatlas.readthedocs.io/
License: BSD 3-Clause
Author: becavin-lab
Requires-Python: >=3.12
Classifier: License :: Other/Proprietary License
Classifier: Programming Language :: Python :: 3
Classifier: Programming Language :: Python :: 3.12
Requires-Dist: multiqc (>=1.10,<2.0)
Requires-Dist: rpy2 (>=3.6.1,<4.0.0)
Requires-Dist: scanpy (>=1.9)
Requires-Dist: scikit-learn (>=1.3)
Project-URL: Documentation, https://checkatlas.readthedocs.io/
Project-URL: Repository, https://github.com/becavin-lab/checkatlas/
